addonev2/__init__.py
addonev2/main.py
addonev2-1.0.0.dist-info/LICENSE
addonev2-1.0.0.dist-info/METADATA
addonev2-1.0.0.dist-info/WHEEL
addonev2-1.0.0.dist-info/top_level.txt
addonev2-1.0.0.dist-info/RECORD
