Metadata-Version: 2.1
Name: addonev2
Version: 1.0.0
Summary: A simple package to add 1 to a given number
Home-page: https://github.com/yourusername/addone
Author: Your Name
Author-email: your_email@example.com
Classifier: Programming Language :: Python :: 3
Classifier: License :: OSI Approved :: MIT License
Classifier: Operating System :: OS Independent
Requires-Python: >=3.6
License-File: LICENSE
